rcedit/__init__.py
rcedit/rcedit.py
rcedit-0.6.dist-info/LICENSE
rcedit-0.6.dist-info/METADATA
rcedit-0.6.dist-info/WHEEL
rcedit-0.6.dist-info/top_level.txt
rcedit-0.6.dist-info/RECORD
