Metadata-Version: 2.1
Name: rcedit
Version: 0.6
Summary: Programmatic access to Research Catalogue web interface
Home-page: https://github.com/grrrr/rcedit
Author: Thomas Grill
Author-email: gr@grrrr.org
Project-URL: Bug Tracker, https://github.com/grrrr/rcedit/issues
Classifier: Programming Language :: Python :: 3
Classifier: License :: OSI Approved :: GNU General Public License v3 or later (GPLv3+)
Classifier: Operating System :: OS Independent
Requires-Python: >=3.6
License-File: LICENSE
Requires-Dist: requests
